trainlog/__init__.py
trainlog/_version.py
trainlog/io.py
trainlog/logger.py
trainlog/logs.py
trainlog/ops.py
trainlog-0.2.dist-info/LICENSE
trainlog-0.2.dist-info/METADATA
trainlog-0.2.dist-info/WHEEL
trainlog-0.2.dist-info/top_level.txt
trainlog-0.2.dist-info/RECORD
