Metadata-Version: 2.1
Name: trainlog
Version: 0.2
Summary: A simple logging library, designed for deep learning
Home-page: https://github.com/DouglasOrr/TrainLog
Author: Douglas Orr
License: MIT
Platform: UNKNOWN
